README.md
setup.py
feathery/__init__.py
feathery/client.py
feathery/constants.py
feathery/polling.py
feathery/utils.py
feathery.egg-info/PKG-INFO
feathery.egg-info/SOURCES.txt
feathery.egg-info/dependency_links.txt
feathery.egg-info/top_level.txt